trip/__init__.py
trip/__version__.py
trip/adapters.py
trip/api.py
trip/compat.py
trip/exceptions.py
trip/models.py
trip/sessions.py
trip/utils.py
trip/contrib/__init__.py
trip/contrib/socks.py
trip-0.0.10.dist-info/DESCRIPTION.rst
trip-0.0.10.dist-info/METADATA
trip-0.0.10.dist-info/RECORD
trip-0.0.10.dist-info/WHEEL
trip-0.0.10.dist-info/metadata.json
trip-0.0.10.dist-info/top_level.txt
