Metadata-Version: 2.0
Name: trip
Version: 0.0.10
Summary: Async HTTP for humans, coroutine Requests.
Home-page: https://github.com/littlecodersh/trip
Author: LittleCoder
Author-email: i7meavnktqegm1b@qq.com
License: Apache 2.0
Keywords: coroutine requests http spider
Platform: UNKNOWN
Classifier: Development Status :: 3 - Alpha
Classifier: Intended Audience :: Developers
Classifier: Topic :: Software Development :: Libraries :: Python Modules
Classifier: License :: OSI Approved :: MIT License
Classifier: Programming Language :: Python :: 2
Classifier: Programming Language :: Python :: 3
Requires-Dist: requests (>=2.18.4)
Requires-Dist: tornado (==4.5.3)
